runstream/__init__.py
runstream/api.py
runstream/model.py
runstream/observable.py
runstream/runstream_client.py
runstream-0.2.0.dist-info/LICENSE
runstream-0.2.0.dist-info/METADATA
runstream-0.2.0.dist-info/WHEEL
runstream-0.2.0.dist-info/RECORD
